psnawp_api/__init__.py
psnawp_api/core/__init__.py
psnawp_api/core/authenticator.py
psnawp_api/core/psnawp_exceptions.py
psnawp_api/core/request_builder.py
psnawp_api/models/__init__.py
psnawp_api/models/client.py
psnawp_api/models/game_entitlements.py
psnawp_api/models/game_title.py
psnawp_api/models/group/__init__.py
psnawp_api/models/group/group.py
psnawp_api/models/group/group_datatypes.py
psnawp_api/models/listing/__init__.py
psnawp_api/models/listing/pagination_iterator.py
psnawp_api/models/search/__init__.py
psnawp_api/models/search/games_search.py
psnawp_api/models/search/games_search_datatypes.py
psnawp_api/models/search/universal_search.py
psnawp_api/models/search/users_result_datatypes.py
psnawp_api/models/search/users_search.py
psnawp_api/models/title_stats.py
psnawp_api/models/trophies/__init__.py
psnawp_api/models/trophies/trophy.py
psnawp_api/models/trophies/trophy_constants.py
psnawp_api/models/trophies/trophy_group.py
psnawp_api/models/trophies/trophy_summary.py
psnawp_api/models/trophies/trophy_titles.py
psnawp_api/models/trophies/trophy_utils.py
psnawp_api/models/user.py
psnawp_api/psnawp.py
psnawp_api/py.typed
psnawp_api/utils/__init__.py
psnawp_api/utils/endpoints.py
psnawp_api/utils/misc.py
psnawp-3.0.0.dist-info/AUTHORS.md
psnawp-3.0.0.dist-info/LICENSE.md
psnawp-3.0.0.dist-info/METADATA
psnawp-3.0.0.dist-info/WHEEL
psnawp-3.0.0.dist-info/RECORD
