Metadata-Version: 2.3
Name: psnawp
Version: 3.0.0
Summary: Python API Wrapper for PlayStation Network API.
License: # PlayStation API Python (PSNAWP)
Keywords: PSN,PlayStation
Author: Yoshikage Kira
Author-email: 8bit_yoshikage_kira@proton.me
Requires-Python: >=3.10, <4.0
Classifier: Development Status :: 5 - Production/Stable
Classifier: Intended Audience :: Developers
Classifier: License :: OSI Approved :: MIT License
Classifier: Operating System :: OS Independent
Classifier: Programming Language :: Python :: 3.10
Classifier: Programming Language :: Python :: 3.11
Classifier: Programming Language :: Python :: 3.12
Classifier: Programming Language :: Python :: 3.13
Classifier: Programming Language :: Python
Classifier: Topic :: Software Development :: Libraries :: Python Modules
Requires-Dist: pycountry (>=24.6.1,<25.0.0)
Requires-Dist: pyrate-limiter (>=3.7.0,<4.0.0)
Requires-Dist: requests (>=2.32.3,<3.0.0)
Requires-Dist: typing-extensions (>=4.12.2,<5.0.0)
Project-URL: Documentation, https://psnawp.readthedocs.io/en/latest/
Project-URL: Homepage, https://github.com/isFakeAccount/psnawp
Project-URL: Repository, https://github.com/isFakeAccount/psnawp
Project-URL: changelog, https://github.com/isFakeAccount/psnawp/commits/master/
